[{"Name":"MINNAAR Greg","Position":1,"Time":"02:03.817","Gap":0.0},{"Name":"BRAYTON Adam","Position":2,"Time":"02:04.398","Gap":0.581},{"Name":"HART Danny","Position":3,"Time":"02:05.417","Gap":1.6},{"Name":"GWIN Aaron","Position":4,"Time":"02:06.112","Gap":2.295},{"Name":"WILLIAMSON Greg","Position":5,"Time":"02:06.835","Gap":3.018},{"Name":"GREENLAND Laurie","Position":6,"Time":"02:06.919","Gap":3.102},{"Name":"BROSNAN Troy","Position":7,"Time":"02:07.107","Gap":3.29},{"Name":"PAYET Florent","Position":8,"Time":"02:07.503","Gap":3.686},{"Name":"GUTIERREZ VILLEGAS Marcelo","Position":9,"Time":"02:07.636","Gap":3.819},{"Name":"THIRION Remi","Position":10,"Time":"02:08.052","Gap":4.235},{"Name":"MARIN TRILLO Alex","Position":11,"Time":"02:08.211","Gap":4.394},{"Name":"SHAW Luca","Position":12,"Time":"02:08.329","Gap":4.512},{"Name":"VERGIER Loris","Position":13,"Time":"02:08.595","Gap":4.778},{"Name":"FAIRCLOUGH Brendan","Position":14,"Time":"02:08.624","Gap":4.807},{"Name":"COULANGES Benoit","Position":15,"Time":"02:08.700","Gap":4.883},{"Name":"ATWILL Philip","Position":16,"Time":"02:09.001","Gap":5.184},{"Name":"BRYCELAND Josh","Position":17,"Time":"02:09.278","Gap":5.461},{"Name":"GALLAGHER Kenta","Position":18,"Time":"02:09.465","Gap":5.648},{"Name":"FEARON Connor","Position":19,"Time":"02:09.624","Gap":5.807},{"Name":"TRUMMER David","Position":20,"Time":"02:09.980","Gap":6.163}]